linex_hash/__init__.py
linex_hash-0.1.3.dist-info/LICENSE
linex_hash-0.1.3.dist-info/METADATA
linex_hash-0.1.3.dist-info/WHEEL
linex_hash-0.1.3.dist-info/top_level.txt
linex_hash-0.1.3.dist-info/RECORD
