Metadata-Version: 2.2
Name: linex_hash
Version: 0.1.3
Summary: A custom hash function library with salt, iterations, and XOR operations
Home-page: https://github.com/lopeklol/linex_hash
Author: lopeklol
Classifier: Programming Language :: Python :: 3
Classifier: License :: OSI Approved :: MIT License
Classifier: Operating System :: OS Independent
Requires-Python: >=3.6
License-File: LICENSE
Dynamic: author
Dynamic: classifier
Dynamic: home-page
Dynamic: requires-python
Dynamic: summary
